slotixmcp/__init__.py
slotixmcp/client.py
slotixmcp/server.py
slotixmcp/resources/__init__.py
slotixmcp/tools/__init__.py
slotixmcp-0.3.0.dist-info/METADATA
slotixmcp-0.3.0.dist-info/WHEEL
slotixmcp-0.3.0.dist-info/entry_points.txt
slotixmcp-0.3.0.dist-info/licenses/LICENSE
slotixmcp-0.3.0.dist-info/RECORD
