Metadata-Version: 2.1
Name: slotixmcp
Version: 0.3.0
Summary: MCP Server for Slotix - AI-powered appointment management integration
Project-URL: Homepage, https://slotix.it
Project-URL: Repository, https://github.com/slotix/SlotixMCP
Project-URL: Documentation, https://github.com/slotix/SlotixMCP#readme
Author-email: Slotix <support@slotix.it>
License: MIT
License-File: LICENSE
Keywords: ai,appointments,chatgpt,claude,mcp,slotix
Classifier: Development Status :: 4 - Beta
Classifier: Intended Audience :: Developers
Classifier: License :: OSI Approved :: MIT License
Classifier: Programming Language :: Python :: 3
Classifier: Programming Language :: Python :: 3.10
Classifier: Programming Language :: Python :: 3.11
Classifier: Programming Language :: Python :: 3.12
Requires-Python: >=3.10
Requires-Dist: httpx>=0.27.0
Requires-Dist: mcp>=1.0.0
Requires-Dist: pydantic>=2.0.0
